ordered_set.py
ordered_set-3.1.dist-info/LICENSE.txt
ordered_set-3.1.dist-info/METADATA
ordered_set-3.1.dist-info/RECORD
ordered_set-3.1.dist-info/WHEEL
ordered_set-3.1.dist-info/top_level.txt
