Metadata-Version: 2.1
Name: ordered-set
Version: 3.1
Summary: A MutableSet that remembers its order, so that every entry has an index.
Home-page: https://github.com/LuminosoInsight/ordered-set
Maintainer: Robyn Speer
Maintainer-email: rspeer@luminoso.com
License: MIT-LICENSE
Platform: any
Classifier: Development Status :: 5 - Production/Stable
Classifier: Intended Audience :: Developers
Classifier: License :: OSI Approved :: MIT License
Classifier: Programming Language :: Python
Classifier: Programming Language :: Python :: 2
Classifier: Programming Language :: Python :: 2.7
Classifier: Programming Language :: Python :: 3
Classifier: Programming Language :: Python :: 3.4
Classifier: Programming Language :: Python :: 3.5
Classifier: Programming Language :: Python :: 3.6
Classifier: Programming Language :: Python :: 3.7
Classifier: Programming Language :: Python :: Implementation :: CPython
Classifier: Programming Language :: Python :: Implementation :: PyPy
Requires-Python: >=2.7
